rclpy/_dummy.cpython-313-x86_64-linux-gnu.so
ros_rclpy-9.1.2.data/data/lib/python3.13/site-packages/rclpy/__init__.py
ros_rclpy-9.1.2.data/data/lib/python3.13/site-packages/rclpy/_rclpy_pybind11.cpython-313-x86_64-linux-gnu.so
ros_rclpy-9.1.2.data/data/lib/python3.13/site-packages/rclpy/callback_groups.py
ros_rclpy-9.1.2.data/data/lib/python3.13/site-packages/rclpy/client.py
ros_rclpy-9.1.2.data/data/lib/python3.13/site-packages/rclpy/clock.py
ros_rclpy-9.1.2.data/data/lib/python3.13/site-packages/rclpy/clock_type.py
ros_rclpy-9.1.2.data/data/lib/python3.13/site-packages/rclpy/constants.py
ros_rclpy-9.1.2.data/data/lib/python3.13/site-packages/rclpy/context.py
ros_rclpy-9.1.2.data/data/lib/python3.13/site-packages/rclpy/duration.py
ros_rclpy-9.1.2.data/data/lib/python3.13/site-packages/rclpy/event_handler.py
ros_rclpy-9.1.2.data/data/lib/python3.13/site-packages/rclpy/exceptions.py
ros_rclpy-9.1.2.data/data/lib/python3.13/site-packages/rclpy/executors.py
ros_rclpy-9.1.2.data/data/lib/python3.13/site-packages/rclpy/expand_topic_name.py
ros_rclpy-9.1.2.data/data/lib/python3.13/site-packages/rclpy/guard_condition.py
ros_rclpy-9.1.2.data/data/lib/python3.13/site-packages/rclpy/logging.py
ros_rclpy-9.1.2.data/data/lib/python3.13/site-packages/rclpy/logging_service.py
ros_rclpy-9.1.2.data/data/lib/python3.13/site-packages/rclpy/node.py
ros_rclpy-9.1.2.data/data/lib/python3.13/site-packages/rclpy/parameter.py
ros_rclpy-9.1.2.data/data/lib/python3.13/site-packages/rclpy/parameter_client.py
ros_rclpy-9.1.2.data/data/lib/python3.13/site-packages/rclpy/parameter_event_handler.py
ros_rclpy-9.1.2.data/data/lib/python3.13/site-packages/rclpy/parameter_service.py
ros_rclpy-9.1.2.data/data/lib/python3.13/site-packages/rclpy/publisher.py
ros_rclpy-9.1.2.data/data/lib/python3.13/site-packages/rclpy/py.typed
ros_rclpy-9.1.2.data/data/lib/python3.13/site-packages/rclpy/qos.py
ros_rclpy-9.1.2.data/data/lib/python3.13/site-packages/rclpy/qos_event.py
ros_rclpy-9.1.2.data/data/lib/python3.13/site-packages/rclpy-9.1.2-py3.13.egg-info/PKG-INFO
ros_rclpy-9.1.2.data/data/lib/python3.13/site-packages/rclpy-9.1.2-py3.13.egg-info/SOURCES.txt
ros_rclpy-9.1.2.data/data/lib/python3.13/site-packages/rclpy-9.1.2-py3.13.egg-info/dependency_links.txt
ros_rclpy-9.1.2.data/data/lib/python3.13/site-packages/rclpy-9.1.2-py3.13.egg-info/top_level.txt
ros_rclpy-9.1.2.dist-info/METADATA
ros_rclpy-9.1.2.dist-info/WHEEL
ros_rclpy-9.1.2.dist-info/top_level.txt
ros_rclpy-9.1.2.dist-info/RECORD
