Metadata-Version: 2.4
Name: ros-rclpy
Version: 9.1.2
Summary: Wheel for the rclpy (ros-rclpy) ROS 2 package.
Requires-Dist: ros-rcl-lifecycle~=10.1.3
Requires-Dist: ros-rmw~=7.8.2
Requires-Dist: ros-rosidl-runtime-c~=4.9.5
Requires-Dist: ros-lifecycle-msgs~=2.3.0
Requires-Dist: ros-rcl-yaml-param-parser~=10.1.3
Requires-Dist: ros-builtin-interfaces~=2.3.0
Requires-Dist: pyyaml
Requires-Dist: ros-rcl-interfaces~=2.3.0
Requires-Dist: ros-type-description-interfaces~=2.3.0
Requires-Dist: ros-rmw-implementation~=3.0.4
Requires-Dist: ros-rcl-logging-interface~=3.2.3
Requires-Dist: ros-rcl-action~=10.1.3
Requires-Dist: typing-extensions
Requires-Dist: ros-rcl~=10.1.3
Requires-Dist: ros-service-msgs~=2.3.0
Requires-Dist: ros-rosgraph-msgs~=2.3.0
Requires-Dist: ros-ament-index-python~=1.11.0
Requires-Dist: ros-rpyutils~=0.6.3
Requires-Dist: ros-unique-identifier-msgs~=2.7.0
Requires-Dist: ros-action-msgs~=2.3.0
Requires-Dist: ros-wheels-bootstrapper
Provides-Extra: fastrtps
Requires-Dist: ros-rmw-fastrtps-cpp~=9.3.3; extra == "fastrtps"
Dynamic: description
Dynamic: description-content-type
Dynamic: provides-extra
Dynamic: requires-dist
Dynamic: summary
